Metadata-Version: 2.1
Name: lxwisbadwei
Version: 0.1
Summary: clinical trial information retriver
Home-page: https://gitee.com/badwei/
Author: lxwbadwei
Author-email: 1211304872@qq.com
License: MIT
Platform: UNKNOWN
